{
  "runId": "20260721_091220",
  "universeCount": 3721,
  "fetchedCount": 3720,
  "priceFilteredCount": 1325,
  "filteredCount": 987,
  "outputRows": 987,
  "splitCount": 2,
  "cappedByVolume": false,
  "minVolumeThreshold": 10000,
  "maxSymbolsPerFile": 500,
  "maxTotalSymbols": 1000,
  "errorCount": 0,
  "rateLimitCount": 0,
  "successRate": 0.999731255038968,
  "cacheHitCount": 0,
  "yahooFetchTargetCount": 3721,
  "filters": {
    "PRICE_THRESHOLD": 1000,
    "MIN_VOLUME_THRESHOLD": 10000
  },
  "thresholds": {
    "MIN_SUCCESS_RATE": 0.95,
    "MAX_ERROR_COUNT": 200,
    "MAX_429_COUNT": 100
  }
}